codenerix_geodata/__init__.py
codenerix_geodata/admin.py
codenerix_geodata/apps.py
codenerix_geodata/forms.py
codenerix_geodata/models.py
codenerix_geodata/urls.py
codenerix_geodata/views.py
codenerix_geodata/data/GeoLite2-City-Locations-en.csv.bz2
codenerix_geodata/data/GeoLite2-City-Locations-es.csv.bz2
codenerix_geodata/data/GeoLite2-Country-Locations-en.csv.bz2
codenerix_geodata/data/GeoLite2-Country-Locations-es.csv.bz2
codenerix_geodata/management/__init__.py
codenerix_geodata/management/__pycache__/__init__.cpython-310.pyc
codenerix_geodata/management/__pycache__/__init__.cpython-311.pyc
codenerix_geodata/management/__pycache__/__init__.cpython-35.pyc
codenerix_geodata/management/__pycache__/__init__.cpython-38.pyc
codenerix_geodata/management/__pycache__/__init__.cpython-39.pyc
codenerix_geodata/management/commands/__init__.py
codenerix_geodata/management/commands/populate_geodata.py
codenerix_geodata/management/commands/__pycache__/__init__.cpython-311.pyc
codenerix_geodata/management/commands/__pycache__/__init__.cpython-35.pyc
codenerix_geodata/management/commands/__pycache__/populate_geodata.cpython-311.pyc
codenerix_geodata/management/commands/__pycache__/populate_geodata.cpython-35.pyc
codenerix_geodata/migrations/0001_initial.py
codenerix_geodata/migrations/0002_auto_20170921_1206.py
codenerix_geodata/migrations/0003_auto_20180118_1209.py
codenerix_geodata/migrations/__init__.py
codenerix_geodata/migrations/__pycache__/0001_initial.cpython-310.pyc
codenerix_geodata/migrations/__pycache__/0001_initial.cpython-311.pyc
codenerix_geodata/migrations/__pycache__/0001_initial.cpython-35.pyc
codenerix_geodata/migrations/__pycache__/0001_initial.cpython-38.pyc
codenerix_geodata/migrations/__pycache__/0001_initial.cpython-39.pyc
codenerix_geodata/migrations/__pycache__/0002_auto_20170921_1206.cpython-310.pyc
codenerix_geodata/migrations/__pycache__/0002_auto_20170921_1206.cpython-311.pyc
django_codenerix_geodata-4.0.5.dist-info/LICENSE
django_codenerix_geodata-4.0.5.dist-info/METADATA
django_codenerix_geodata-4.0.5.dist-info/WHEEL
django_codenerix_geodata-4.0.5.dist-info/top_level.txt
django_codenerix_geodata-4.0.5.dist-info/RECORD
